aiomcache/__init__.py
aiomcache/client.py
aiomcache/constants.py
aiomcache/exceptions.py
aiomcache/pool.py
aiomcache/py.typed
aiomcache-0.8.2.dist-info/LICENSE
aiomcache-0.8.2.dist-info/METADATA
aiomcache-0.8.2.dist-info/WHEEL
aiomcache-0.8.2.dist-info/top_level.txt
aiomcache-0.8.2.dist-info/RECORD
