Metadata-Version: 2.1
Name: aiomcache
Version: 0.8.2
Summary: Minimal pure python memcached client
Home-page: https://github.com/aio-libs/aiomcache/
Author: Nikolay Kim
Author-email: fafhrd91@gmail.com
Maintainer: Nikolay Kim <fafhrd91@gmail.com>, Andrew Svetlov <andrew.svetlov@gmail.com>
Maintainer-email: aio-libs@googlegroups.com
License: BSD
Classifier: License :: OSI Approved :: BSD License
Classifier: Intended Audience :: Developers
Classifier: Programming Language :: Python
Classifier: Programming Language :: Python :: 3.8
Classifier: Programming Language :: Python :: 3.9
Classifier: Programming Language :: Python :: 3.10
Classifier: Programming Language :: Python :: 3.11
Classifier: Programming Language :: Python :: 3.12
Classifier: Operating System :: POSIX
Classifier: Operating System :: MacOS :: MacOS X
Classifier: Operating System :: Microsoft :: Windows
Classifier: Environment :: Web Environment
Classifier: Framework :: AsyncIO
Requires-Python: >=3.8
License-File: LICENSE
Requires-Dist: typing_extensions>=4; python_version < "3.11"
